src/basker.py
basker-1.0.0.dist-info/METADATA
basker-1.0.0.dist-info/WHEEL
basker-1.0.0.dist-info/licenses/LICENSE
basker-1.0.0.dist-info/RECORD
