Metadata-Version: 2.1
Name: basker
Version: 1.0.0
Summary: Simple and clean background tasks.
Project-URL: Homepage, https://github.com/twanwalpot/basker
Project-URL: Bug Tracker, https://github.com/twanwalpot/basker/issues
Author-email: Twan Walpot <twan@walpot.dev>
License: MIT License
Classifier: License :: OSI Approved :: MIT License
Classifier: Operating System :: OS Independent
Classifier: Programming Language :: Python :: 3
Requires-Python: >=3.7
